setup.py
distributions_SH/Binomialdistribution.py
distributions_SH/Gaussiandistribution.py
distributions_SH/Generaldistribution.py
distributions_SH/__init__.py
distributions_SH.egg-info/PKG-INFO
distributions_SH.egg-info/SOURCES.txt
distributions_SH.egg-info/dependency_links.txt
distributions_SH.egg-info/not-zip-safe
distributions_SH.egg-info/top_level.txt