Metadata-Version: 1.0
Name: distributions-SH
Version: 0.1
Summary: General distribution, Gaussian distributions, and Binomial distribution 
Home-page: UNKNOWN
Author: Scarlett Huang
Author-email: scarlett0413@outlook.com
License: UNKNOWN
Platform: UNKNOWN
